geocat/datafiles/__init__.py
geocat_datafiles-2025.7.1.dist-info/licenses/LICENSE
geocat_datafiles-2025.7.1.dist-info/METADATA
geocat_datafiles-2025.7.1.dist-info/WHEEL
geocat_datafiles-2025.7.1.dist-info/top_level.txt
geocat_datafiles-2025.7.1.dist-info/RECORD
