Metadata-Version: 2.4
Name: geocat.datafiles
Version: 2025.7.1
Summary: GeoCAT-datafiles hosts data files used by other GeoCAT packages to test or demonstrate functionality
Author-email: GeoCAT Team <geocat@ucar.edu>
License-Expression: Apache-2.0
Project-URL: issue-tracker, https://github.com/NCAR/geocat-datafiles/issues
Project-URL: source-code, https://github.com/NCAR/geocat-datafiles
Classifier: Operating System :: OS Independent
Classifier: Intended Audience :: Science/Research
Classifier: Programming Language :: Python
Classifier: Programming Language :: Python :: 3
Classifier: Programming Language :: Python :: 3.10
Classifier: Programming Language :: Python :: 3.11
Classifier: Programming Language :: Python :: 3.12
Classifier: Programming Language :: Python :: 3.13
Classifier: Topic :: Scientific/Engineering
Requires-Python: >=3.10
License-File: LICENSE
Requires-Dist: pooch
Dynamic: license-file
